tomon_sdk/__init__.py
tomon_sdk/bot.py
tomon_sdk/events.py
tomon_sdk/gateway.py
tomon_sdk/model.py
tomon_sdk/network/__init__.py
tomon_sdk/network/api.py
tomon_sdk/network/http.py
tomon_sdk/network/route.py
tomon_sdk/network/session.py
tomon_sdk/network/ws.py
tomon_sdk/utils/__init__.py
tomon_sdk/utils/observable.py
tomon_sdk-0.1.6.dist-info/LICENSE
tomon_sdk-0.1.6.dist-info/METADATA
tomon_sdk-0.1.6.dist-info/WHEEL
tomon_sdk-0.1.6.dist-info/top_level.txt
tomon_sdk-0.1.6.dist-info/RECORD
