Metadata-Version: 2.1
Name: tomon-sdk
Version: 0.1.6
Summary: A simple development kit for Tomon bot.
Home-page: https://github.com/tomon-world/tomon-sdk-py
Author: Tomon Team
Author-email: qiang.l.x@gmail.com
License: UNKNOWN
Keywords: TOMON
Platform: UNKNOWN
Classifier: Development Status :: 3 - Alpha
Classifier: Intended Audience :: Developers
Classifier: Programming Language :: Python :: 3
Classifier: License :: OSI Approved :: MIT License
Classifier: Operating System :: OS Independent
Classifier: Programming Language :: Python :: 3
Classifier: Programming Language :: Python :: 3.4
Classifier: Programming Language :: Python :: 3.5
Classifier: Programming Language :: Python :: 3.6
Classifier: Programming Language :: Python :: 3.7
Requires-Dist: aiohttp
Requires-Dist: node-events
Requires-Dist: ws4py
